<?xml version="1.0" encoding="utf-8" ?>
<dwsync>
<file name="1712314059.png" server="sites.sidoarjokab.go.id/public_html/" local="133567876595878207" remote="133613623800000000" Dst="0" />
<file name="1712314088.png" server="sites.sidoarjokab.go.id/public_html/" local="133567876881807628" remote="133613623800000000" Dst="0" />
<file name="1712314107.png" server="sites.sidoarjokab.go.id/public_html/" local="133567889428153465" remote="133613623800000000" Dst="0" />
<file name="1712314059.png" server="diskominfo.sidoarjokab.go.id//tempWeb/" local="133567876595878207" remote="133603233000000000" Dst="0" />
<file name="1712314088.png" server="diskominfo.sidoarjokab.go.id//tempWeb/" local="133567876881807628" remote="133603233000000000" Dst="0" />
<file name="1712314107.png" server="diskominfo.sidoarjokab.go.id//tempWeb/" local="133567889428153465" remote="133603233000000000" Dst="0" />
<file name="1712314059.png" server="ppid.sidoarjokab.go.id/public_html/" local="133567876595878207" remote="133608266400000000" Dst="0" />
<file name="1712314088.png" server="ppid.sidoarjokab.go.id/public_html/" local="133567876881807628" remote="133608266400000000" Dst="0" />
<file name="1712314107.png" server="ppid.sidoarjokab.go.id/public_html/" local="133567889428153465" remote="133608266400000000" Dst="0" />
</dwsync>